{
  "strategy": "yes",
  "timeframe": "5m",
  "total_trades": 618,
  "wins": 187,
  "losses": 431,
  "draws": 0,
  "win_rate": 30.258899676375407,
  "avg_profit": -0.13503945102367276,
  "total_profit": -25.158949693333334,
  "total_profit_abs": -37.73842454,
  "sharpe_ratio": -2.8076144628756854,
  "sortino_ratio": -5.302768992551161,
  "calmar_ratio": -4.985790165776367,
  "max_drawdown": 26.779498613333335,
  "max_drawdown_abs": 40.16924792,
  "trade_duration_avg": 139,
  "starting_balance": 150.0,
  "final_balance": 112.26157546,
  "timerange": "20250422-20260417",
  "pairlist": [
    "XRP/USDT",
    "ETH/USDT",
    "HOME/USDT"
  ],
  "backtest_start": "2025-04-22 00:00:00",
  "backtest_end": "2026-04-17 00:00:00",
  "expectancy": -0.06106541187702266,
  "profit_factor": 0.7655370915122492,
  "max_consecutive_wins": 6,
  "max_consecutive_losses": 17
}